Metadata-Version: 2.1
Name: term-image
Version: 0.7.2
Summary: Display images in the terminal
Home-page: https://github.com/AnonymouX47/term-image
Author: Toluwaleke Ogundipe
Author-email: anonymoux47@gmail.com
License: MIT
Project-URL: Changelog, https://github.com/AnonymouX47/term-image/blob/main/CHANGELOG.md
Project-URL: Documentation, https://term-image.readthedocs.io/
Project-URL: Funding, https://github.com/AnonymouX47/term-image#donate
Project-URL: Source, https://github.com/AnonymouX47/term-image
Project-URL: Tracker, https://github.com/AnonymouX47/term-image/issues
Keywords: image,terminal,viewer,PIL,Pillow,console,xterm,library,cli,tui,ANSI,ASCII-Art,kitty,iterm2,sixel,graphics
Classifier: Environment :: Console
Classifier: License :: OSI Approved :: MIT License
Classifier: Intended Audience :: Developers
Classifier: Operating System :: POSIX :: Linux
Classifier: Operating System :: MacOS
Classifier: Operating System :: Android
Classifier: Operating System :: Microsoft :: Windows
Classifier: Programming Language :: Python :: 3
Classifier: Programming Language :: Python :: 3.7
Classifier: Programming Language :: Python :: 3.8
Classifier: Programming Language :: Python :: 3.9
Classifier: Programming Language :: Python :: 3.10
Classifier: Programming Language :: Python :: 3.11
Classifier: Programming Language :: Python :: 3.12
Classifier: Programming Language :: Python :: 3 :: Only
Classifier: Topic :: Software Development :: Libraries
Classifier: Topic :: Terminals :: Terminal Emulators/X Terminals
Classifier: Topic :: Multimedia :: Graphics :: Viewers
Requires-Python: >=3.7
License-File: LICENSE
Requires-Dist: pillow<11,>=9.1
Requires-Dist: requests<3,>=2.23
